setup.cfg
setup.py
ogres/__init__.py
ogres/basics.py
ogres.egg-info/PKG-INFO
ogres.egg-info/SOURCES.txt
ogres.egg-info/dependency_links.txt
ogres.egg-info/top_level.txt
ogres.egg-info/zip-safe
ogres/layers/__init__.py
ogres/layers/convolutions.py
ogres/layers/recurrent.py