Metadata-Version: 1.1
Name: ogres
Version: 0.0.2
Summary: Thin tensorflow wrapper. Requires tensorflow
Home-page: https://github.com/butternutdog/ogres
Author: ogres@butternutdog.com
Author-email: ogres@butternutdog.com
License: MIT
Download-URL: https://github.com/butternutdog/ogres/tarball/0.0.2
Platform: any
Classifier: Operating System :: OS Independent
Classifier: Programming Language :: Python
Classifier: License :: OSI Approved :: MIT License
Classifier: Development Status :: 3 - Alpha
